proxibulk/__init__.py
proxibulk/actions.py
proxibulk/cli.py
proxibulk/cli_add.py
proxibulk/colors.py
proxibulk/connection_handlers.py
proxibulk/connection_handlers_bulk.py
proxibulk/logging_utils.py
proxibulk/main.py
proxibulk/modem.py
proxibulk/probe.py
proxibulk/utils.py
proxibulk/version.py
proxibulk/connection_handlers/__init__.py
proxidize_mx2-1.1.0.dist-info/licenses/LICENSE
proxidize_mx2-1.1.0.dist-info/METADATA
proxidize_mx2-1.1.0.dist-info/WHEEL
proxidize_mx2-1.1.0.dist-info/entry_points.txt
proxidize_mx2-1.1.0.dist-info/top_level.txt
proxidize_mx2-1.1.0.dist-info/RECORD
