Metadata-Version: 2.4
Name: proxidize_mx2
Version: 1.1.0
Summary: Proxidize MX2 Manager - Professional proprietary modem management tool by Proxidize Ltd.
Author-email: "Proxidize Ltd." <support@proxidize.com>
License: Proprietary
Project-URL: Homepage, https://proxidize.com
Project-URL: Documentation, https://pypi.org/project/proxidize_mx2/
Project-URL: PyPI, https://pypi.org/project/proxidize_mx2/
Classifier: Development Status :: 5 - Production/Stable
Classifier: Environment :: Console
Classifier: Intended Audience :: Developers
Classifier: License :: Other/Proprietary License
Classifier: Operating System :: OS Independent
Classifier: Programming Language :: Python :: 3
Classifier: Programming Language :: Python :: 3.11
Classifier: Programming Language :: Python :: 3.12
Classifier: Programming Language :: Python :: 3.13
Classifier: Topic :: System :: Networking
Classifier: Topic :: System :: Systems Administration
Requires-Python: >=3.11
License-File: LICENSE
Requires-Dist: requests>=2.25.0
Requires-Dist: colorama>=0.4.4
Requires-Dist: pyfiglet>=0.8.0
Requires-Dist: tqdm>=4.62.0
Dynamic: license-file
